{ "mood": [
       {
              "name": "Clear",
              "ids" :[
                     "800"
              ],
              "icon": "09d",             
              "color": "#FADF81",
              "moods": [
                     "joy", 
                     "happiness", 
                     "optimism",
                     "adventure",
                     "relaxed",
                     "energy"
              ]
       },
       {
              "name": "Clouds",
              "ids" :[
                     "801",
                     "802",
                     "803",
                     "804"
              ],
              "icon": "09d",             
              "color": "#ADE3B6",
              "moods": [
                     "calm", 
                     "focus", 
                     "mystery",
                     "reflection",
                     "serenity",
                     "melancholy"
              ]
       },
       {
              "name": "Drizzle",
              "ids" :[
                     "300",
                     "301",
                     "302",
                     "310",
                     "311",
                     "312",
                     "313",
                     "314",
                     "321"
              ],
              "icon": "09d",             
              "color": "#7DD9E6",
              "moods": [
                     "calm", 
                     "refreshed", 
                     "peaceful",
                     "reflection",
                     "loneliness",
                     "sadness"
              ]
       },
       {
              "name": "Rain",
              "ids" :[
                     "500",
                     "501",
                     "502",
                     "503",
                     "504",
                     "511",
                     "520",
                     "521",
                     "522",
                     "531"
              ],
              "icon": "09d",             
              "color": "#4A96EF",
              "moods": [
                     "sorrow",
                     "loneliness",
                     "sadness",
                     "meditation",
                     "contemplation",
                     "coziness", 
                     "comfort"
              ]
       },
       {
              "name": "Thunderstorm",
              "ids" :[
                     "200",
                     "301",
                     "302",
                     "210",
                     "211",
                     "212",
                     "221", 
                     "230", 
                     "231", 
                     "232" 
              ],
              "icon": "09d",             
              "color": "#3D7CE2",
              "moods": [
                     "melancholy", 
                     "power",
                     "excitement",
                     "drama",
                     "reflection",
                     "wonder",
                     "intense"
              ]
       },
       {
              "name": "Snow",
              "ids" :[
                     "600",
                     "601",
                     "602",
                     "611",
                     "612",
                     "613",
                     "615",
                     "321"
              ],
              "icon": "09d",             
              "color": "#fafafa",
              "moods": [
                     "wonder", 
                     "cozy",
                     "serenity",
                     "playful",
                     "joy",
                     "warm"
              ]
       },
       {
         "name": "Mist",
         "icon": "09d",
         "color": "#7370E8",
         "moods": [
           "mysterious",
           "calm",
           "loneliness",
           "uncertain",
           "introspection",
           "romantic"
         ]
       }
]}